pprintjson/__init__.py
pprintjson/__main__.py
pprintjson/pprintjson.py
pprintjson/test_pprintjson.py
pprintjson-1.4.2.dist-info/LICENSE
pprintjson-1.4.2.dist-info/METADATA
pprintjson-1.4.2.dist-info/WHEEL
pprintjson-1.4.2.dist-info/entry_points.txt
pprintjson-1.4.2.dist-info/top_level.txt
pprintjson-1.4.2.dist-info/RECORD
