Metadata-Version: 2.1
Name: pprintjson
Version: 1.4.2
Summary: A json pretty printer for python
Home-page: https://github.com/clarketm/pprintjson
Author: Travis Clarke
Author-email: travis.m.clarke@gmail.com
License: UNKNOWN
Platform: UNKNOWN
Classifier: Programming Language :: Python :: 3
Classifier: Programming Language :: Python :: 3.6
Classifier: Programming Language :: Python :: 3.7
Classifier: Programming Language :: Python :: 3.8
Classifier: License :: OSI Approved :: MIT License
Classifier: Operating System :: OS Independent
Requires-Python: >=3.6
Provides-Extra: simplejson
